tributary/__init__.py
tributary/_version.py
tributary/base.py
tributary/thread.py
tributary/utils.py
tributary/functional/__init__.py
tributary/functional/input.py
tributary/functional/output.py
tributary/functional/utils.py
tributary/incubating/__init__.py
tributary/incubating/ast_experiments.py
tributary/lazy/__init__.py
tributary/lazy/base.py
tributary/lazy/dd3.py
tributary/lazy/decorator.py
tributary/lazy/graph.py
tributary/lazy/node.py
tributary/lazy/utils.py
tributary/lazy/calculations/__init__.py
tributary/lazy/calculations/basket.py
tributary/lazy/calculations/finance.py
tributary/lazy/calculations/ops.py
tributary/lazy/calculations/rolling.py
tributary/lazy/calculations/utils.py
tributary/lazy/control/__init__.py
tributary/lazy/control/control.py
tributary/lazy/control/utils.py
tributary/lazy/input/__init__.py
tributary/lazy/output/__init__.py
tributary/lazy/output/output.py
tributary/parser/__init__.py
tributary/streaming/__init__.py
tributary/streaming/base.py
tributary/streaming/dd3.py
tributary/streaming/graph.py
tributary/streaming/node.py
tributary/streaming/scheduler.py
tributary/streaming/serialize.py
tributary/streaming/utils.py
tributary/streaming/calculations/__init__.py
tributary/streaming/calculations/basket.py
tributary/streaming/calculations/finance.py
tributary/streaming/calculations/ops.py
tributary/streaming/calculations/rolling.py
tributary/streaming/calculations/utils.py
tributary/streaming/control/__init__.py
tributary/streaming/control/control.py
tributary/streaming/control/utils.py
tributary/streaming/input/__init__.py
tributary/streaming/input/file.py
tributary/streaming/input/http.py
tributary/streaming/input/input.py
tributary/streaming/input/kafka.py
tributary/streaming/input/postgres.py
tributary/streaming/input/process.py
tributary/streaming/input/socketio.py
tributary/streaming/input/sse.py
tributary/streaming/input/ws.py
tributary/streaming/output/__init__.py
tributary/streaming/output/email.py
tributary-0.2.1.dist-info/LICENSE
tributary-0.2.1.dist-info/METADATA
tributary-0.2.1.dist-info/WHEEL
tributary-0.2.1.dist-info/top_level.txt
tributary-0.2.1.dist-info/RECORD
