Metadata-Version: 2.1
Name: tributary
Version: 0.2.1
Summary: Streaming reactive and dataflow graphs in Python
Home-page: https://github.com/streamlet-dev/tributary
Author: Tim Paine
Author-email: t.paine154@gmail.com
License: Apache 2.0
Keywords: streaming lazy graph dag dataflow reactive
Classifier: Development Status :: 3 - Alpha
Classifier: Programming Language :: Python :: 3
Classifier: Programming Language :: Python :: 3.7
Classifier: Programming Language :: Python :: 3.8
Classifier: Programming Language :: Python :: 3.9
Classifier: Programming Language :: Python :: 3.10
Requires-Python: >=3.7
License-File: LICENSE
Requires-Dist: aioconsole (>=0.2.1)
Requires-Dist: aiofiles (>=0.4.0)
Requires-Dist: aiohttp (>=3.5.4)
Requires-Dist: aiohttp-sse (>=2.0)
Requires-Dist: aiohttp-sse-client (>=0.2.0)
Requires-Dist: aiokafka (>=0.6.0)
Requires-Dist: aiostream (>=0.3.1)
Requires-Dist: asyncpg (>=0.20.1)
Requires-Dist: beautifulsoup4 (>=4.9.1)
Requires-Dist: boltons (>=20.1.0)
Requires-Dist: emails (>=0.5.15)
Requires-Dist: frozendict (>=1.2)
Requires-Dist: future (>=0.17.1)
Requires-Dist: gevent (>=1.3.7)
Requires-Dist: graphviz (>=0.10.1)
Requires-Dist: ipython (>=7.0.1)
Requires-Dist: ipydagred3 (>=0.1.5)
Requires-Dist: numpy (>=1.15.3)
Requires-Dist: pandas (>=0.19.0)
Requires-Dist: scipy (>1.2.0)
Requires-Dist: six (>=1.11.0)
Requires-Dist: socketIO-client-nexus (>=0.7.6)
Requires-Dist: sympy (>=1.5.1)
Requires-Dist: temporal-cache (>=0.0.6)
Requires-Dist: tornado (>=5.1.1)
Requires-Dist: twilio (>=6.50.1)
Provides-Extra: dev
Requires-Dist: black (>=23) ; extra == 'dev'
Requires-Dist: check-manifest ; extra == 'dev'
Requires-Dist: flake8 (>=3.7.8) ; extra == 'dev'
Requires-Dist: flake8-black (>=0.2.1) ; extra == 'dev'
Requires-Dist: mock ; extra == 'dev'
Requires-Dist: pybind11 (>=2.4.0) ; extra == 'dev'
Requires-Dist: pytest (>=4.3.0) ; extra == 'dev'
Requires-Dist: pytest-cov (>=2.6.1) ; extra == 'dev'
Requires-Dist: Sphinx (>=1.8.4) ; extra == 'dev'
Requires-Dist: sphinx-markdown-builder (>=0.5.2) ; extra == 'dev'
Requires-Dist: aioconsole (>=0.2.1) ; extra == 'dev'
Requires-Dist: aiofiles (>=0.4.0) ; extra == 'dev'
Requires-Dist: aiohttp (>=3.5.4) ; extra == 'dev'
Requires-Dist: aiohttp-sse (>=2.0) ; extra == 'dev'
Requires-Dist: aiohttp-sse-client (>=0.2.0) ; extra == 'dev'
Requires-Dist: aiokafka (>=0.6.0) ; extra == 'dev'
Requires-Dist: aiostream (>=0.3.1) ; extra == 'dev'
Requires-Dist: asyncpg (>=0.20.1) ; extra == 'dev'
Requires-Dist: beautifulsoup4 (>=4.9.1) ; extra == 'dev'
Requires-Dist: boltons (>=20.1.0) ; extra == 'dev'
Requires-Dist: emails (>=0.5.15) ; extra == 'dev'
Requires-Dist: frozendict (>=1.2) ; extra == 'dev'
Requires-Dist: future (>=0.17.1) ; extra == 'dev'
Requires-Dist: gevent (>=1.3.7) ; extra == 'dev'
Requires-Dist: graphviz (>=0.10.1) ; extra == 'dev'
Requires-Dist: ipython (>=7.0.1) ; extra == 'dev'
Requires-Dist: ipydagred3 (>=0.1.5) ; extra == 'dev'
Requires-Dist: numpy (>=1.15.3) ; extra == 'dev'
Requires-Dist: pandas (>=0.19.0) ; extra == 'dev'
Requires-Dist: scipy (>1.2.0) ; extra == 'dev'
Requires-Dist: six (>=1.11.0) ; extra == 'dev'
Requires-Dist: socketIO-client-nexus (>=0.7.6) ; extra == 'dev'
Requires-Dist: sympy (>=1.5.1) ; extra == 'dev'
Requires-Dist: temporal-cache (>=0.0.6) ; extra == 'dev'
Requires-Dist: tornado (>=5.1.1) ; extra == 'dev'
Requires-Dist: twilio (>=6.50.1) ; extra == 'dev'
Provides-Extra: develop
Requires-Dist: black (>=23) ; extra == 'develop'
Requires-Dist: check-manifest ; extra == 'develop'
Requires-Dist: flake8 (>=3.7.8) ; extra == 'develop'
Requires-Dist: flake8-black (>=0.2.1) ; extra == 'develop'
Requires-Dist: mock ; extra == 'develop'
Requires-Dist: pybind11 (>=2.4.0) ; extra == 'develop'
Requires-Dist: pytest (>=4.3.0) ; extra == 'develop'
Requires-Dist: pytest-cov (>=2.6.1) ; extra == 'develop'
Requires-Dist: Sphinx (>=1.8.4) ; extra == 'develop'
Requires-Dist: sphinx-markdown-builder (>=0.5.2) ; extra == 'develop'
Requires-Dist: aioconsole (>=0.2.1) ; extra == 'develop'
Requires-Dist: aiofiles (>=0.4.0) ; extra == 'develop'
Requires-Dist: aiohttp (>=3.5.4) ; extra == 'develop'
Requires-Dist: aiohttp-sse (>=2.0) ; extra == 'develop'
Requires-Dist: aiohttp-sse-client (>=0.2.0) ; extra == 'develop'
Requires-Dist: aiokafka (>=0.6.0) ; extra == 'develop'
Requires-Dist: aiostream (>=0.3.1) ; extra == 'develop'
Requires-Dist: asyncpg (>=0.20.1) ; extra == 'develop'
Requires-Dist: beautifulsoup4 (>=4.9.1) ; extra == 'develop'
Requires-Dist: boltons (>=20.1.0) ; extra == 'develop'
Requires-Dist: emails (>=0.5.15) ; extra == 'develop'
Requires-Dist: frozendict (>=1.2) ; extra == 'develop'
Requires-Dist: future (>=0.17.1) ; extra == 'develop'
Requires-Dist: gevent (>=1.3.7) ; extra == 'develop'
Requires-Dist: graphviz (>=0.10.1) ; extra == 'develop'
Requires-Dist: ipython (>=7.0.1) ; extra == 'develop'
Requires-Dist: ipydagred3 (>=0.1.5) ; extra == 'develop'
Requires-Dist: numpy (>=1.15.3) ; extra == 'develop'
Requires-Dist: pandas (>=0.19.0) ; extra == 'develop'
Requires-Dist: scipy (>1.2.0) ; extra == 'develop'
Requires-Dist: six (>=1.11.0) ; extra == 'develop'
Requires-Dist: socketIO-client-nexus (>=0.7.6) ; extra == 'develop'
Requires-Dist: sympy (>=1.5.1) ; extra == 'develop'
Requires-Dist: temporal-cache (>=0.0.6) ; extra == 'develop'
Requires-Dist: tornado (>=5.1.1) ; extra == 'develop'
Requires-Dist: twilio (>=6.50.1) ; extra == 'develop'
Provides-Extra: functional
Requires-Dist: confluent-kafka (>=0.11.6) ; extra == 'functional'
Requires-Dist: websocket-client (>=0.57.0) ; extra == 'functional'
